nsfc/__init__.py
nsfc/bin/__init__.py
nsfc/bin/build.py
nsfc/bin/crawl.py
nsfc/bin/main.py
nsfc/bin/query.py
nsfc/bin/report.py
nsfc/db/__init__.py
nsfc/db/manager.py
nsfc/db/model.py
nsfc/src/__init__.py
nsfc/src/letpub.py
nsfc/src/medsci.py
nsfc/src/official.py
nsfc/util/__init__.py
nsfc/util/parse_data.py
nsfc/version/version.json
nsfc-2.0.4.dist-info/LICENSE
nsfc-2.0.4.dist-info/METADATA
nsfc-2.0.4.dist-info/WHEEL
nsfc-2.0.4.dist-info/entry_points.txt
nsfc-2.0.4.dist-info/top_level.txt
nsfc-2.0.4.dist-info/RECORD
