Metadata-Version: 2.1
Name: nsfc
Version: 2.0.4
Summary: 国家自然科学基金数据查询系统
Home-page: https://github.com/suqingdong/nsfc
Author: suqingdong
Author-email: suqingdong1114@gmail.com
License: BSD License
Project-URL: Documentation, https://nsfc.readthedocs.io
Project-URL: Tracker, https://github.com/suqingdong/nsfc/issues
Platform: UNKNOWN
Classifier: Development Status :: 5 - Production/Stable
Classifier: Operating System :: OS Independent
Classifier: Intended Audience :: Developers
Classifier: License :: OSI Approved :: MIT License
Classifier: Programming Language :: Python
Classifier: Programming Language :: Python :: 3
Classifier: Programming Language :: Python :: 3.8
Classifier: Topic :: Software Development :: Libraries
Requires-Dist: click
Requires-Dist: img2pdf
Requires-Dist: openpyxl
Requires-Dist: requests
Requires-Dist: sqlalchemy
Requires-Dist: prettytable
Requires-Dist: human-readable
Requires-Dist: webrequests
Requires-Dist: simple-loggers
